[
    {
        "name": "放松休憩头罩",
        "iconname": "农夫护肩",
        "rank": "史诗",
        "kind": "布甲(护肩)",
        "trade": "无法交易",
        "level": "105",
        "naiku": "0/0",
        "gold": "0",
        "chuurek": "0",
        "value1": "物理防御力 1065<br>力量 100<br>智力 149<br>体力 100<br>精神 149",
        "value4": "冒险家名望 748",
        "value5": "",
        "value6": "技能攻击力 +34%",
        "transable": "1",
        "buffer": "",
        "shujuj1": "1078",
        "tatakae1": "",
        "shujujlv1": "1",
        "linxuan1": "前冲时30秒内生成杂草，HP最大值+10%(冷却时间10秒，最大重叠1次)",
        "shujuj2": "1078",
        "tatakae2": "",
        "shujujlv2": "1",
        "linxuan2": "身旁有杂草的场合下，所有属性抗性+20，所有异常状态抗性+10%，命中率+10%",
        "shujuj3": "1078",
        "tatakae3": "",
        "shujujlv3": "1",
        "linxuan3": "HP最大值+1500<br>MP最大值-200",
        "shujuj4": "1078",
        "tatakae4": "",
        "shujujlv4": "1",
        "linxuan4": "感电抗性+3%<br>中毒抗性+3%<br>出血抗性+3%",
        "flavor": "",
        "MAX": "4312"
    },
    {
        "name": "无限努力布鞋",
        "iconname": "农夫鞋子",
        "rank": "史诗",
        "kind": "布甲(鞋)",
        "trade": "无法交易",
        "level": "105",
        "naiku": "0/0",
        "gold": "0",
        "chuurek": "0",
        "value1": "物理防御力 799<br>力量 100<br>智力 136<br>体力 100<br>精神 136",
        "value4": "冒险家名望 748",
        "value5": "",
        "value6": "移动速度+4%<br>技能攻击力 +29%",
        "transable": "1",
        "buffer": "",
        "shujuj1": "1347",
        "tatakae1": "",
        "shujujlv1": "1",
        "linxuan1": "跳跃落地时落下西瓜，20内赋予武器冰属性攻击，冰属性抗性+10，移动速度+10%(最大叠加1次)",
        "shujuj2": "1347",
        "tatakae2": "",
        "shujujlv2": "1",
        "linxuan2": "跳跃状态下适用霸体护甲",
        "shujuj3": "1347",
        "tatakae3": "",
        "shujujlv3": "1",
        "linxuan3": "跳跃时1%几率解除自身的异常状态(冷却时间60秒)",
        "shujuj4": "1347",
        "tatakae4": "",
        "shujujlv4": "1",
        "linxuan4": "跳跃力+50 <br>跳跃状态回避率+3%",
        "flavor": "这是我的一小步，却是莱蒂族的一大步",
        "MAX": "5388"
    },
    {
        "name": "紧抓季节腰带",
        "iconname": "农夫腰带",
        "rank": "史诗",
        "kind": "布甲(腰带)",
        "trade": "无法交易",
        "level": "105",
        "naiku": "0/0",
        "gold": "0",
        "chuurek": "0",
        "value1": "物理防御力 532<br>力量 100<br>智力 131<br>体力 100<br>精神 136",
        "value4": "冒险家名望 748",
        "value5": "",
        "value6": "负重上限+3kg<br>技能攻击力 +12%",
        "transable": "1",
        "buffer": "",
        "shujuj1": "1347",
        "tatakae1": "",
        "shujujlv1": "1",
        "linxuan1": "死亡时角色会悲伤地哭泣<br>复活时30秒内增加30%攻击速度、30%移动速度、45%释放速度(冷却时间60秒)",
        "shujuj2": "1347",
        "tatakae2": "",
        "shujujlv2": "1",
        "linxuan2": "复活时300秒内被攻击时恢复10%HP(最大5次)",
        "shujuj3": "1347",
        "tatakae3": "",
        "shujujlv3": "1",
        "linxuan3": "诅咒抗性+25%<br>所有异常耐性-5%",
        "shujuj4": "1347",
        "tatakae4": "",
        "shujujlv4": "1",
        "linxuan4": "暗属性抗性+20",
        "flavor": "看起来还能用！",
        "MAX": "5388"
    },
    {
        "name": "尽职尽责上衣",
        "iconname": "农夫上衣",
        "rank": "史诗",
        "kind": "布甲(上衣)",
        "trade": "无法交易",
        "level": "105",
        "naiku": "0/0",
        "gold": "0",
        "chuurek": "0",
        "value1": "物理防御力 1597<br>力量 100<br>智力 161<br>体力 100<br>精神 161",
        "value4": "冒险家名望 748",
        "value5": "",
        "value6": "技能攻击力 +12%<br>装备的总成长等级每40提升3%的技能攻击力<br>- 神话装备装着时不适用<br>- 上衣、手镯、耳环三个部位只能适用1次此属性，取最高效果值",
        "transable": "1",
        "buffer": "",
        "shujuj1": "1212",
        "tatakae1": "",
        "shujujlv1": "1",
        "linxuan1": "攻击时15%几率投掷最大5个农作物<br>每投掷1个农作物时物理、魔法暴击率+3%，持续30秒(最大叠加5层)",
        "shujuj2": "1212",
        "tatakae2": "",
        "shujujlv2": "1",
        "linxuan2": "攻击时有10%几率投掷可收割的大农作物(20秒冷却时间，最大叠加1层)<br>根据不同的作物获得不同效果<br>- 洋白菜：恢复18%HP<br>- 大南瓜：恢复15%HP和MP<br>- 大萝卜：恢复18%MP<br>- 大茄子：恢复15%HP并强化身体30秒<br>- 大白菜：恢复15%MP并使得头脑清醒30秒",
        "shujuj3": "1212",
        "tatakae3": "",
        "shujujlv3": "1",
        "linxuan3": "最大负重+2kg<br>HP最大值+300",
        "shujuj4": "1212",
        "tatakae4": "",
        "shujujlv4": "1",
        "linxuan4": "最大负重+3kg<br>MP最大值+500",
        "flavor": "现在起，让我们创造属于我们的世界吧",
        "MAX": "4848"
    },
    {
        "name": "晴热痕迹下装",
        "iconname": "农夫裤子",
        "rank": "史诗",
        "kind": "布甲(下装)",
        "trade": "无法交易",
        "level": "105",
        "naiku": "0/0",
        "gold": "0",
        "chuurek": "0",
        "value1": "物理防御力 1331<br>力量 100<br>智力 161<br>体力 100<br>精神 161",
        "value4": "冒险家名望 748",
        "value5": "",
        "value6": "技能攻击力 +12%",
        "transable": "1",
        "buffer": "",
        "shujuj1": "1212",
        "tatakae1": "",
        "shujujlv1": "1",
        "linxuan1": "被击时有25%几率使得角色10秒内进入惊吓状态，物理、魔法防御力+10%(最大叠加2次)",
        "shujuj2": "1212",
        "tatakae2": "",
        "shujujlv2": "1",
        "linxuan2": "惊吓状态下被击时，30秒内增加20%攻击速度，20%移动速度和30%释放速度(最多叠加1层)",
        "shujuj3": "1212",
        "tatakae3": "",
        "shujujlv3": "1",
        "linxuan3": "回避率+5%<br>混乱抗性+15%",
        "shujuj4": "1212",
        "tatakae4": "",
        "shujujlv4": "1",
        "linxuan4": "物理防御力+2000<br>魔法防御力-500",
        "flavor": "身上的汗水和污泥可是农民骄傲的象征！",
        "MAX": "4848"
    },
    {
        "name": "努力的光辉结晶",
        "iconname": "农夫魔法石",
        "rank": "史诗",
        "kind": "魔法石",
        "trade": "无法交易",
        "level": "105",
        "naiku": "0/0",
        "gold": "0",
        "chuurek": "0",
        "value1": "力量 172<br>智力 172<br>体力 172<br>精神 172",
        "value4": "冒险家名望 748",
        "value5": "",
        "value6": "技能攻击力 +12%",
        "transable": "",
        "buffer": "",
        "shujuj1": "1212",
        "tatakae1": "",
        "shujujlv1": "1",
        "linxuan1": "进入地下城时生成被攻击5次就会被破坏的草莓光环(冷却时间30秒)<br>- 草莓光环状态下被击伤害-15%",
        "shujuj2": "1212",
        "tatakae2": "",
        "shujujlv2": "1",
        "linxuan2": "草莓光环状态下消耗品的HP恢复效果+20%",
        "shujuj3": "1212",
        "tatakae3": "",
        "shujujlv3": "1",
        "linxuan3": "魔法防御力+2000<br>物理防御力-500",
        "shujuj4": "1212",
        "tatakae4": "",
        "shujujlv4": "1",
        "linxuan4": "攻击时5%几率10秒内增加7%命中率(冷却时间10秒)",
        "flavor": "",
        "MAX": "4848"
    },
    {
        "name": "满满的一大桶",
        "iconname": "农夫辅助装备",
        "rank": "史诗",
        "kind": "辅助装备",
        "trade": "无法交易",
        "level": "105",
        "naiku": "0/0",
        "gold": "0",
        "chuurek": "0.0",
        "value1": "力量 149<br>智力 149<br>体力 149<br>精神 149",
        "value4": "冒险家名望 748",
        "value5": "",
        "value6": "技能攻击力 +12%",
        "transable": "",
        "buffer": "",
        "shujuj1": "1347",
        "tatakae1": "",
        "shujujlv1": "1",
        "linxuan1": "每40秒生成持续40秒的小云<br>- 地图上存在小云的时候获得持续40秒的增益效果<br>- 暗属性抗性+15<br>- 冰属性抗性 +15<br>- 攻击速度+10%，释放速度+15%",
        "shujuj2": "1347",
        "tatakae2": "",
        "shujujlv2": "1",
        "linxuan2": "地图上存在小云的场合下赋予武器冰属性和暗属性攻击",
        "shujuj3": "1347",
        "tatakae3": "",
        "shujujlv3": "1",
        "linxuan3": "冰冻抗性+3%<br>灼伤抗性-1.5%",
        "shujuj4": "1347",
        "tatakae4": "",
        "shujujlv4": "1",
        "linxuan4": "攻击时有3%几率赋予敌人冰冻状态1秒(冷却时间1秒)",
        "flavor": "",
        "MAX": "5388"
    },
    {
        "name": "渔获气息",
        "iconname": "农夫耳环",
        "rank": "史诗",
        "kind": "耳环",
        "trade": "无法交易",
        "level": "105",
        "naiku": "0/0",
        "gold": "0",
        "chuurek": "0",
        "value1": "力量 172<br>智力 172<br>体力 172<br>精神 172",
        "value4": "冒险家名望 748",
        "value5": "",
        "value6": "技能攻击力 +12%<br>装备的总成长等级每40提升3%的技能攻击力<br>- 神话装备装着时不适用<br>- 上衣、手镯、耳环三个部位只能适用1次此属性，取最高效果值",
        "transable": "",
        "buffer": "",
        "shujuj1": "1212",
        "tatakae1": "",
        "shujujlv1": "1",
        "linxuan1": "自身处于异常状态时解除异常状态(冷却时间100秒)",
        "shujuj2": "1212",
        "tatakae2": "",
        "shujujlv2": "1",
        "linxuan2": "全异常状态抗性+25%<br>移动速度-5%",
        "shujuj3": "1212",
        "tatakae3": "",
        "shujujlv3": "1",
        "linxuan3": "攻击时1%几率赋予敌人3秒诅咒状态(冷却时间1秒)",
        "shujuj4": "1212",
        "tatakae4": "",
        "shujujlv4": "1",
        "linxuan4": "攻击速度+5%<br>移动速度+5%<br>释放速度+8%<br>HP最大值-250",
        "flavor": "",
        "MAX": "4848"
    },
    {
        "name": "甜蜜伙伴",
        "iconname": "农夫戒指",
        "rank": "史诗",
        "kind": "戒指",
        "trade": "无法交易",
        "level": "105",
        "naiku": "0/0",
        "gold": "0",
        "chuurek": "0.0",
        "value1": "魔法防御力 4294<br>力量 173<br>智力 173<br>体力 100<br>精神 100",
        "value4": "冒险家名望 748",
        "value5": "",
        "value6": "技能攻击力 +12%",
        "transable": "",
        "buffer": "",
        "shujuj1": "1347",
        "tatakae1": "",
        "shujujlv1": "1",
        "linxuan1": "每40秒生成持续40秒的小太阳<br>- 地图存在小太阳的时候发动持续40秒的buff<br>- 火属性抗性+15<br>- 光属性抗性+15<br>- 移动速度+10%",
        "shujuj2": "1347",
        "tatakae2": "",
        "shujujlv2": "1",
        "linxuan2": "地图存在小太阳的时候，赋予武器火属性和光属性攻击",
        "shujuj3": "1347",
        "tatakae3": "",
        "shujujlv3": "1",
        "linxuan3": "灼伤抗性+3%<br> 冰冻抗性-1.5%",
        "shujuj4": "1347",
        "tatakae4": "",
        "shujujlv4": "1",
        "linxuan4": "攻击时3%几率赋予持续2秒的失明状态(冷却时间1秒)",
        "flavor": "",
        "MAX": "5388"
    },
    {
        "name": "大鱼天堂",
        "iconname": "农夫项链",
        "rank": "史诗",
        "kind": "项链",
        "trade": "无法交易",
        "level": "105",
        "naiku": "0/0",
        "gold": "0",
        "chuurek": "0.0",
        "value1": "魔法防御力 10736<br>力量 100<br>智力 150<br>体力 100<br>精神 222",
        "value4": "冒险家名望 748",
        "value5": "",
        "value6": "技能攻击力 +12%",
        "transable": "",
        "buffer": "",
        "shujuj1": "1212",
        "tatakae1": "",
        "shujujlv1": "1",
        "linxuan1": "HP50%以下时，发动渔夫的加护恢复20%HP(冷却时间40秒)",
        "shujuj2": "1212",
        "tatakae2": "",
        "shujujlv2": "1",
        "linxuan2": "渔夫的加护发动时，30秒内全部异常抗性+20%，回避率+5%",
        "shujuj3": "1212",
        "tatakae3": "",
        "shujujlv3": "1",
        "linxuan3": "出血抗性+1%<br>物理防御力+500",
        "shujuj4": "1212",
        "tatakae4": "",
        "shujujlv4": "1",
        "linxuan4": "每10秒HP最大值+100(最大叠加10次)",
        "flavor": "",
        "MAX": "4848"
    },
    {
        "name": "热情果实",
        "iconname": "农夫手镯",
        "rank": "史诗",
        "kind": "手镯",
        "trade": "无法交易",
        "level": "105",
        "naiku": "0/0",
        "gold": "0",
        "chuurek": "0.0",
        "value1": "魔法防御力 6442<br>力量 150<br>智力 100<br>体力 222<br>精神 100",
        "value4": "冒险家名望 748",
        "value5": "",
        "value6": "技能攻击力 +12%<br>装备的总成长等级每40提升3%的技能攻击力<br>- 神话装备装着时不适用<br>- 上衣、手镯、耳环三个部位只能适用1次此属性，取最高效果值",
        "transable": "",
        "buffer": "",
        "shujuj1": "1212",
        "tatakae1": "",
        "shujujlv1": "1",
        "linxuan1": "MP低于50%时，发动农民的祝福恢复20%的MP（冷却时间40秒）",
        "shujuj2": "1212",
        "tatakae2": "",
        "shujujlv2": "1",
        "linxuan2": "发动农民的祝福时，所有属性抗性+40，回避率+5%，持续30秒 ",
        "shujuj3": "1212",
        "tatakae3": "",
        "shujujlv3": "1",
        "linxuan3": "中毒抗性+1%<br>魔法防御力+500",
        "shujuj4": "1212",
        "tatakae4": "",
        "shujujlv4": "1",
        "linxuan4": "每10秒MP最大值+100(最大叠加10次)",
        "flavor": "",
        "MAX": "4848"
    }
]