[
    {
        "name": "永远沉眠的准备",
        "iconname": "消亡腰带",
        "rank": "史诗",
        "kind": "轻甲(腰带)",
        "trade": "无法交易",
        "level": "105",
        "naiku": "25/25",
        "gold": "15,984",
        "chuurek": "1.2",
        "value1": "物理防御力 1501<br>力量 128<br>智力 118<br>体力 93<br>精神 95",
        "value4": "冒险家名望 748",
        "value5": "",
        "value6": "负重上限+3kg<br>技能攻击力 +12%<br>装备的词条等级合计240时提升1%的技能攻击力<br>- 装备词条等级每40追加增加1%技能攻击力<br>- 装备Lv100以下装备时不适用",
        "transable": "",
        "buffer": "",
        "shujuj1": "1078",
        "tatakae1": "",
        "shujujlv1": "1",
        "linxuan1": "敌人的韧性条处于正常状态时前，使用冰冻状态赋予到灼伤状态的敌人会马上结算灼伤状态的所有伤害(冷却时间4秒)",
        "shujuj2": "1078",
        "tatakae2": "",
        "shujujlv2": "1",
        "linxuan2": "灼伤状态伤害值+15%<br>自身赋予的灼伤状态持续时间+2秒",
        "shujuj3": "1186",
        "tatakae3": "",
        "shujujlv3": "1",
        "linxuan3": "500px范围内每拥有一个灼伤状态的对象，攻击强化 +356(最大叠加10次)",
        "shujuj4": "1186",
        "tatakae4": "",
        "shujujlv4": "1",
        "linxuan4": "MP MAX +945",
        "flavor": "",
        "MAX": "4528"
    },
    {
        "name": "朝向消亡的脚步",
        "iconname": "消亡之靴",
        "rank": "史诗",
        "kind": "轻甲(鞋)",
        "trade": "无法交易",
        "level": "105",
        "naiku": "25/25",
        "gold": "15,984",
        "chuurek": "1.4",
        "value1": "物理防御力 2252<br>力量 128<br>智力 118<br>体力 93<br>精神 95",
        "value4": "冒险家名望 748",
        "value5": "",
        "value6": "移动速度+4%<br>技能攻击力 +29%<br>装备的词条等级合计240时提升1%的技能攻击力<br>- 装备词条等级每40追加增加1%技能攻击力<br>- 装备Lv100以下装备时不适用",
        "transable": "",
        "buffer": "",
        "shujuj1": "808",
        "tatakae1": "",
        "shujujlv1": "1",
        "linxuan1": "最强的伤害型异常状态的伤害加成数值累计55%以上时，技能攻击力+10%",
        "shujuj2": "808",
        "tatakae2": "",
        "shujujlv2": "1",
        "linxuan2": "自身赋予的所有伤害型异常状态持续时间-20%",
        "shujuj3": "1630",
        "tatakae3": "",
        "shujujlv3": "1",
        "linxuan3": "所有属性强化+15<br>所有属性抗性-10",
        "shujuj4": "1186",
        "tatakae4": "",
        "shujujlv4": "1",
        "linxuan4": "技能MP消耗量-7%",
        "flavor": "",
        "MAX": "4432"
    },
    {
        "name": "弥久的时间之沼",
        "iconname": "消亡手镯",
        "rank": "史诗",
        "kind": "手镯",
        "trade": "无法交易",
        "level": "105",
        "naiku": "",
        "gold": "24,864",
        "chuurek": "0.4",
        "value1": "魔法防御力 6442<br>力量 140<br>智力 95<br>体力 207<br>精神 95",
        "value4": "冒险家名望 748",
        "value5": "",
        "value6": "Buff量 +295<br>技能攻击力 +12%<br>这个装备的词条等级每40提升3%的技能攻击力<br>- 神话装备装着时不适用<br>- 上衣、手镯、耳环三个部位只能适用1次此属性，取最高效果值<br><br>装备的词条等级合计240时提升1%的技能攻击力<br>- 装备词条等级每40追加增加1%技能攻击力<br>- 装备Lv100以下装备时不适用",
        "transable": "",
        "buffer": "",
        "shujuj1": "1078",
        "tatakae1": "",
        "shujujlv1": "1",
        "linxuan1": "自身获得睡眠异常状态时，60秒内自身不进入睡眠状态而是获得特殊的不眠症Buff(最大叠加5次)<br><br>不眠症buff状态时适用以下效果<br>- 睡眠抗性数值从0%开始，每减少10%技能攻击力增加4%(最大增加28%)<br>- 适用睡眠状态的装备效果，适用于自身不眠症时，数值会仅适用50%(HP恢复效果以外)<br>- 被击时自身的不眠症叠加次数-1<br>- 每叠加1次不眠症buff，所有速度-5%<br><br>不眠症buff重叠到5层时，不眠症buff解除，随后让自身进入强制的睡眠状态",
        "shujuj2": "1078",
        "tatakae2": "",
        "shujujlv2": "1",
        "linxuan2": "进入地下城后每消耗10000MP，赋予自身一次睡眠状态<br>睡眠抗性-10%",
        "shujuj3": "1630",
        "tatakae3": "",
        "shujujlv3": "1",
        "linxuan3": "物理暴击率+7%<br>魔法暴击率+7%<br>所有异常状态抗性-10%",
        "shujuj4": "1186",
        "tatakae4": "",
        "shujujlv4": "1",
        "linxuan4": "回避率+8%",
        "flavor": "",
        "MAX": "4972"
    }
]